gallerator/.gitignore
gallerator/__init__.py
gallerator/constants.py
gallerator/data_types.py
gallerator/dynimport.py
gallerator/gallery.py
gallerator/generated_set.py
gallerator/main.py
gallerator/media_items.py
gallerator/renderer.py
gallerator/thumbnails.py
gallerator/url_strategy.py
gallerator/video_images.py
gallerator/renderers/renderer_util.py
gallerator/renderers/nanogallery2/download.sh
gallerator/renderers/nanogallery2/nanogallery2.py
gallerator/renderers/nanogallery2/removeDownloaded.sh
gallerator/renderers/nanogallery2/static/.gitignore
gallerator/renderers/nanogallery2/static/README.md
gallerator/renderers/nanogallery2/static/jquery.min.js
gallerator/renderers/nanogallery2/templates/page.html
gallerator/renderers/nanogallery2/templates/page.js
gallerator/renderers/photoswipe/photoswipe.py
gallerator/renderers/photoswipe/static/README.md
gallerator/renderers/photoswipe/static/page.js
gallerator/renderers/photoswipe/static/photoswipe-lightbox.esm.min.js
gallerator/renderers/photoswipe/static/photoswipe.css
gallerator/renderers/photoswipe/static/photoswipe.esm.min.js
gallerator/renderers/photoswipe/static/font-awesome/css/font-awesome.min.css
gallerator/renderers/photoswipe/static/font-awesome/fonts/fontawesome-webfont.woff2
gallerator/renderers/photoswipe/templates/page.css
gallerator/renderers/photoswipe/templates/page.html
gallerator/renderers/static/README.md
gallerator/renderers/static/bootstrap-gallery.css
gallerator/renderers/static/bootstrap.bundle.min.js
gallerator/renderers/static/bootstrap.min.css
gallerator/renderers/static/favicon.ico
gallerator/renderers/static/gallery-32.png
gallerator/renderers/static/gallery-512.png
gallerator/renderers/templates/bootstrap-gallery.html
gallerator/simple/demo.html
gallerator/simple/no_js.py
gallerator/simple/static/README.md
gallerator/simple/static/font-awesome.min.css
gallerator/simple/static/page.css
gallerator/simple/static/page.js
gallerator/simple/static/photoswipe-lightbox.esm.min.js
gallerator-1.0.dist-info/METADATA
gallerator-1.0.dist-info/WHEEL
gallerator-1.0.dist-info/entry_points.txt
gallerator-1.0.dist-info/licenses/LICENSE.txt
gallerator-1.0.dist-info/RECORD
