Metadata-Version: 2.3
Name: gallerator
Version: 1.0
Summary: Generate image galleries
Project-URL: Homepage, https://github.com/pmorch/gallerator
Project-URL: Demos, https://pmorch.github.io/demo-gallerator/
Requires-Python: >=3.12
Requires-Dist: jinja2
Requires-Dist: pillow
Requires-Dist: ruff
Requires-Dist: tqdm
Requires-Dist: vcsi
